odoo/addons/hr_employee_birth_name/README.rst
odoo/addons/hr_employee_birth_name/__init__.py
odoo/addons/hr_employee_birth_name/__manifest__.py
odoo/addons/hr_employee_birth_name/i18n/ar.po
odoo/addons/hr_employee_birth_name/i18n/cs_CZ.po
odoo/addons/hr_employee_birth_name/i18n/de.po
odoo/addons/hr_employee_birth_name/i18n/es.po
odoo/addons/hr_employee_birth_name/i18n/fi.po
odoo/addons/hr_employee_birth_name/i18n/fr.po
odoo/addons/hr_employee_birth_name/i18n/hr.po
odoo/addons/hr_employee_birth_name/i18n/hr_HR.po
odoo/addons/hr_employee_birth_name/i18n/hr_employee_birth_name.pot
odoo/addons/hr_employee_birth_name/i18n/it.po
odoo/addons/hr_employee_birth_name/i18n/lt.po
odoo/addons/hr_employee_birth_name/i18n/nl_NL.po
odoo/addons/hr_employee_birth_name/i18n/pt_BR.po
odoo/addons/hr_employee_birth_name/i18n/ro.po
odoo/addons/hr_employee_birth_name/i18n/sl.po
odoo/addons/hr_employee_birth_name/models/__init__.py
odoo/addons/hr_employee_birth_name/models/hr_employee.py
odoo/addons/hr_employee_birth_name/readme/CONTRIBUTORS.rst
odoo/addons/hr_employee_birth_name/readme/DESCRIPTION.rst
odoo/addons/hr_employee_birth_name/readme/INSTALL.rst
odoo/addons/hr_employee_birth_name/readme/USAGE.rst
odoo/addons/hr_employee_birth_name/static/description/icon.png
odoo/addons/hr_employee_birth_name/static/description/index.html
odoo/addons/hr_employee_birth_name/views/hr_employee_view.xml
odoo12_addon_hr_employee_birth_name-12.0.1.0.0.99.dev6.dist-info/METADATA
odoo12_addon_hr_employee_birth_name-12.0.1.0.0.99.dev6.dist-info/WHEEL
odoo12_addon_hr_employee_birth_name-12.0.1.0.0.99.dev6.dist-info/top_level.txt
odoo12_addon_hr_employee_birth_name-12.0.1.0.0.99.dev6.dist-info/RECORD
